airflow_cli-1.0.4.post0.dist-info/licenses/LICENSE
src/__init__.py
src/_version.py
src/cli.py
src/docker-compose.yml
src/docker_utils.py
src/os_utils.py
airflow_cli-1.0.4.post0.dist-info/METADATA
airflow_cli-1.0.4.post0.dist-info/WHEEL
airflow_cli-1.0.4.post0.dist-info/entry_points.txt
airflow_cli-1.0.4.post0.dist-info/top_level.txt
airflow_cli-1.0.4.post0.dist-info/RECORD
