Metadata-Version: 2.4
Name: airflow-cli
Version: 1.0.4.post0
Summary: 🚀 CLI to manage Apache Airflow in Docker environments with ease
Author-email: LEMA-UFPB <ufpblema@gmail.com>
License: MIT
Project-URL: Homepage, https://github.com/lema-ufpb/airflow-cli
Project-URL: Documentation, https://github.com/lema-ufpb/airflow-cli#readme
Project-URL: Repository, https://github.com/lema-ufpb/airflow-cli
Project-URL: Issues, https://github.com/lema-ufpb/airflow-cli/issues
Keywords: airflow,docker,cli,data-engineering,workflow,orchestration
Classifier: Development Status :: 4 - Beta
Classifier: Intended Audience :: Developers
Classifier: Topic :: Software Development :: Build Tools
Classifier: License :: OSI Approved :: MIT License
Classifier: Programming Language :: Python :: 3
Classifier: Programming Language :: Python :: 3.7
Classifier: Programming Language :: Python :: 3.8
Classifier: Programming Language :: Python :: 3.9
Classifier: Programming Language :: Python :: 3.10
Classifier: Programming Language :: Python :: 3.11
Classifier: Programming Language :: Python :: 3.12
Requires-Python: >=3.7
License-File: LICENSE
Requires-Dist: pyyaml>=5.4.0
Requires-Dist: requests>=2.25.0
Provides-Extra: dev
Requires-Dist: flake8>=4.0.0; extra == "dev"
Requires-Dist: autopep8>=2.0.0; extra == "dev"
Requires-Dist: black>=22.0.0; extra == "dev"
Requires-Dist: pytest>=7.0.0; extra == "dev"
Requires-Dist: pytest-cov>=4.0.0; extra == "dev"
Provides-Extra: linter
Requires-Dist: flake8>=4.0.0; extra == "linter"
Requires-Dist: autopep8>=2.0.0; extra == "linter"
Dynamic: license-file
